eztaskmanager/__init__.py
eztaskmanager/admin.py
eztaskmanager/apps.py
eztaskmanager/locale/it/LC_MESSAGES/django.po
eztaskmanager/management/__init__.py
eztaskmanager/management/commands/__init__.py
eztaskmanager/management/commands/collectcommands.py
eztaskmanager/management/commands/test_command.py
eztaskmanager/management/commands/test_livelogging_command.py
eztaskmanager/management/commands/test_logging_command.py
eztaskmanager/migrations/0001_initial.py
eztaskmanager/migrations/0002_task_scheduled_job_id.py
eztaskmanager/migrations/0003_alter_task_cached_next_ride_alter_task_scheduling.py
eztaskmanager/migrations/__init__.py
eztaskmanager/models.py
eztaskmanager/services/__init__.py
eztaskmanager/services/logger.py
eztaskmanager/services/notifications.py
eztaskmanager/services/queues.py
eztaskmanager/settings.py
eztaskmanager/static/img/iconfinder_ic_wrap_text.png
eztaskmanager/static/img/icons8-double-down-32.png
eztaskmanager/static/img/icons8-new-document-32.png
eztaskmanager/static/js/axios.js
eztaskmanager/static/js/linkify.min.js
eztaskmanager/static/js/menu_filter_collapse.js
eztaskmanager/static/js/vue.js
eztaskmanager/templates/admin/appcommand_changeform.html
eztaskmanager/templates/admin/custom_changeform.html
eztaskmanager/templates/admin/edit_inline/tabular_reports.html
eztaskmanager/templates/live_log_viewer.html
eztaskmanager/templates/log_viewer.html
eztaskmanager/tests/test_admin.py
eztaskmanager/tests/test_logger.py
eztaskmanager/tests/test_models.py
eztaskmanager/tests/test_services.py
eztaskmanager/tests/test_views.py
eztaskmanager/urls.py
eztaskmanager/views.py
django_eztaskmanager-0.5.1.dist-info/METADATA
django_eztaskmanager-0.5.1.dist-info/WHEEL
django_eztaskmanager-0.5.1.dist-info/licenses/AUTHORS.md
django_eztaskmanager-0.5.1.dist-info/licenses/LICENSE.md
django_eztaskmanager-0.5.1.dist-info/RECORD
