Metadata-Version: 2.4
Name: django-eztaskmanager
Version: 0.5.1
Summary: Django application that allows the management of scheduled, long, asynchronous tasks.
License: MIT
License-File: AUTHORS.md
License-File: LICENSE.md
Keywords: async,cron,django,commands,manager,queues,task,timer,scheduling,rq,celery
Author: Guglielmo Celata
Author-email: guglielmo@openpolis.it
Requires-Python: >=3.10
Classifier: Development Status :: 4 - Beta
Classifier: Environment :: Web Environment
Classifier: Framework :: Django
Classifier: Framework :: Django :: 3.2
Classifier: Framework :: Django :: 4.0
Classifier: Framework :: Django :: 4.1
Classifier: Framework :: Django :: 4.2
Classifier: Framework :: Django :: 5.0
Classifier: Intended Audience :: Developers
Classifier: License :: OSI Approved :: MIT License
Classifier: Operating System :: OS Independent
Classifier: Programming Language :: Python
Classifier: Programming Language :: Python :: 3
Classifier: Programming Language :: Python :: 3.10
Classifier: Programming Language :: Python :: 3.11
Classifier: Programming Language :: Python :: 3.12
Classifier: Programming Language :: Python :: 3.13
Classifier: Programming Language :: Python :: 3.14
Classifier: Programming Language :: Python :: 3 :: Only
Classifier: Programming Language :: Python :: 3.8
Classifier: Programming Language :: Python :: 3.9
Classifier: Topic :: Internet :: WWW/HTTP
Classifier: Topic :: Internet :: WWW/HTTP :: Dynamic Content
Provides-Extra: celery
Provides-Extra: django
Provides-Extra: slack
Requires-Dist: celery[redis] (>=5.4.0,<6.0.0) ; extra == "celery"
Requires-Dist: django (>=5.1.4,<6.0.0) ; extra == "django"
Requires-Dist: django-extensions (>=3.2.3,<4.0.0)
Requires-Dist: django-rq (>=3.0.0,<4.0.0)
Requires-Dist: gnureadline (>=8.2.13,<9.0.0)
Requires-Dist: pytz (>=2024.2,<2025.0)
Requires-Dist: rq-scheduler (>=0.14.0,<0.15.0)
Requires-Dist: slack-sdk (>=3.27.1,<4.0.0) ; extra == "slack"
Requires-Dist: whitenoise (>=6.8.1,<7.0.0)
Project-URL: Documentation, https://django-eztaskmanager.readthedocs.io
Project-URL: Homepage, https://github.com/openpolis/django-eztaskmanager.git
Project-URL: Repository, https://github.com/openpolis/django-eztaskmanager.git
